lehd/__init__.py
lehd/lehd.py
lehd/utils.py
lehd-0.0.2.dist-info/LICENSE
lehd-0.0.2.dist-info/METADATA
lehd-0.0.2.dist-info/WHEEL
lehd-0.0.2.dist-info/top_level.txt
lehd-0.0.2.dist-info/RECORD
