Metadata-Version: 2.1
Name: lehd
Version: 0.0.2
Summary: a library for downloading LEHD data
Home-page: https://github.com/jamaps/lehd
Author: Jeff Allen
Author-email: jeff.allen@utoronto.ca
License: UNKNOWN
Platform: UNKNOWN
Classifier: Programming Language :: Python :: 3
Classifier: License :: OSI Approved :: MIT License
Classifier: Operating System :: OS Independent
Requires-Python: >=3.6
Requires-Dist: pandas (>=1.0)
Requires-Dist: urllib3 (>1.25)
Requires-Dist: shapely (>=1.7.0)
Requires-Dist: geopandas (>=0.7.0)
